pyrevizto/__init__.py
pyrevizto/comments.py
pyrevizto/issues.py
pyrevizto/licenses.py
pyrevizto/project_roles.py
pyrevizto/projects.py
pyrevizto/pyrevizto.py
pyrevizto/reports.py
pyrevizto/sheets.py
pyrevizto/stamps.py
pyrevizto/users.py
pyrevizto-0.92.dist-info/LICENSE
pyrevizto-0.92.dist-info/METADATA
pyrevizto-0.92.dist-info/WHEEL
pyrevizto-0.92.dist-info/top_level.txt
pyrevizto-0.92.dist-info/RECORD
