Metadata-Version: 2.2
Name: pyrevizto
Version: 0.92
Summary: pyRevizto is a library designed specifically for Python developers who work with Revizto, a popular platform for BIM collaboration and issue tracking. By leveraging pyRevizto, developers can streamline their workflows and significantly enhance the capabilities of Revizto through automation.
Home-page: https://github.com/umarkhalid007/pyRevizto
Author: Umar Khalid
Project-URL: Bug Tracker, https://github.com/umarkhalid007/pyRevizto/issues
Keywords: Revizto
Requires-Python: >=3.6
License-File: LICENSE
Requires-Dist: requests>=2.28.2
Requires-Dist: python-dotenv>=1.0.1
Dynamic: author
Dynamic: description
Dynamic: description-content-type
Dynamic: home-page
Dynamic: keywords
Dynamic: project-url
Dynamic: requires-dist
Dynamic: requires-python
Dynamic: summary
